simvue_fds/__init__.py
simvue_fds/connector.py
simvue_fds-2.0.4.dist-info/METADATA
simvue_fds-2.0.4.dist-info/WHEEL
simvue_fds-2.0.4.dist-info/licenses/LICENSE
simvue_fds-2.0.4.dist-info/RECORD
