Metadata-Version: 2.4
Name: simvue-fds
Version: 2.0.4
Summary: Connector to allow you to easily add Simvue tracking and monitoring to FDS (Fire Dynamics Simulator) simulations.
License-File: LICENSE
Keywords: tracking,monitoring,metrics,alerting,metrics-gathering
Author: Matt Field
Author-email: matthew.field@ukaea.uk
Requires-Python: >=3.10,<3.14
Classifier: Development Status :: 5 - Production/Stable
Classifier: Intended Audience :: Science/Research
Classifier: License :: OSI Approved :: Apache Software License
Classifier: Natural Language :: English
Classifier: Operating System :: Unix
Classifier: Operating System :: Microsoft :: Windows
Classifier: Programming Language :: Python :: 3
Classifier: Programming Language :: Python :: 3.10
Classifier: Programming Language :: Python :: 3.11
Classifier: Programming Language :: Python :: 3.12
Classifier: Programming Language :: Python :: 3.13
Classifier: Topic :: Scientific/Engineering
Classifier: Topic :: System :: Monitoring
Classifier: Topic :: Utilities
Classifier: Typing :: Typed
Requires-Dist: f90nml (>1.4.3)
Requires-Dist: fdsreader (>=1.11.7,<2.0.0)
Requires-Dist: simvue (>=2.2.2)
Requires-Dist: simvue-connector (>=1.0.0)
Requires-Dist: ukaea-multiparser (>=1.0.5)
Project-URL: Documentation, https://docs.simvue.io
Project-URL: Homepage, https://simvue.io
Project-URL: Repository, https://github.com/simvue-io/connectors-fds
